setup.py
rawr/__init__.py
rawr/network.py
rawr.egg-info/PKG-INFO
rawr.egg-info/SOURCES.txt
rawr.egg-info/dependency_links.txt
rawr.egg-info/entry_points.txt
rawr.egg-info/not-zip-safe
rawr.egg-info/top_level.txt