Metadata-Version: 1.0
Name: rawr
Version: 0.1.1
Summary: Growl Network Interface
Home-page: https://github.com/d0ugal/rawr
Author: Dougal Matthews
Author-email: dougal85@gmail.com
License: MIT
Keywords: growl
Platform: UNKNOWN
Classifier: Development Status :: 4 - Beta
Classifier: Intended Audience :: Developers
Classifier: License :: OSI Approved :: MIT License
Classifier: Programming Language :: Python :: 2
Classifier: Programming Language :: Python :: 2.4
Classifier: Programming Language :: Python :: 2.5
Classifier: Programming Language :: Python :: 2.6
Classifier: Programming Language :: Python :: 2.7
